aiohttp_tor/__init__.py
aiohttp_tor/connector.py
aiohttp_tor/installer.py
aiohttp_tor/process.py
aiohttp_tor/py.typed
aiohttp_tor/typedefs.py
aiohttp_tor/web.py
aiohttp_tor-0.1.0.dist-info/licenses/LICENSE
aiohttp_tor-0.1.0.dist-info/METADATA
aiohttp_tor-0.1.0.dist-info/WHEEL
aiohttp_tor-0.1.0.dist-info/top_level.txt
aiohttp_tor-0.1.0.dist-info/RECORD
