Metadata-Version: 2.4
Name: aiohttp-tor
Version: 0.1.0
Summary: Tor utilities for using with aiohttp
Author-email: Vizonex <VizonexBusiness@gmail.com>
Requires-Python: >=3.10
License-File: LICENSE
Requires-Dist: aiostem>=0.4.5
Requires-Dist: aiohttp
Requires-Dist: aiohttp-socks
Requires-Dist: aiofiles
Requires-Dist: async_lru
Dynamic: license-file
